<?xml version="1.0"?>
<openerp>
    <data>

    <!-- Phonecall Categories Form View  -->
    <record id="crm_phonecall_type_action" model="ir.actions.act_window">
        <field name="name">Phonecall Types</field>
        <field name="res_model">crm.phonecall.type</field>
        <field name="view_type">form</field>
    </record>

    <menuitem action="crm_phonecall_type_action" name="Types"
        id="menu_crm_case_phonecall_type" parent="crm.menu_crm_config_phonecall" groups="base.group_no_one"/>

    <!-- Phonecalls Tree View -->
    <record model="ir.ui.view" id="crm_case_phone_tree_view">
        <field name="name">CRM - Phone Calls Tree</field>
        <field name="model">crm.phonecall</field>
        <field name="inherit_id" ref="crm.crm_case_phone_tree_view"/>
        <field name="arch" type="xml">
            <field name="categ_id" position='before'>
                <field name="type_id"/>
            </field>
        </field>
    </record>

    <!-- Phonecalls Form View -->
    <record model="ir.ui.view" id="crm_case_phone_form_view">
        <field name="name">CRM - Phone Call Form</field>
        <field name="model">crm.phonecall</field>
        <field name="inherit_id" ref="crm.crm_case_phone_form_view"/>
        <field name="arch" type="xml">
            <field name="categ_id" position='before'>
                <field name="type_id"/>
            </field>
        </field>
    </record>

    <!--Logged Phonecalls Tree View -->
    <record model="ir.ui.view" id="crm_case_inbound_phone_tree_view">
        <field name="name">CRM - Logged Phone Calls Tree</field>
        <field name="model">crm.phonecall</field>
        <field name="inherit_id" ref="crm.crm_case_inbound_phone_tree_view"/>
        <field name="arch" type="xml">
            <field name="categ_id" position='before'>
                <field name="type_id"/>
            </field>
        </field>
    </record>

    <!-- Phonecalls Search View  -->
    <record id="view_crm_case_phonecalls_filter" model="ir.ui.view">
        <field name="name">CRM - Phone Calls Search</field>
        <field name="model">crm.phonecall</field>
        <field name="inherit_id" ref="crm.view_crm_case_phonecalls_filter"/>
        <field name="arch" type="xml">
            <field name="section_id" position='after'>
                <field name="type_id"/>
            </field>
            <group expand="0" string="Group By">
                <filter string="Type" context="{'group_by':'type_id'}"/>
            </group>
        </field>
    </record>

    </data>
</openerp>
