<openerp>
    <data>
        <record model="ir.ui.view" id="sale_order_validity">
            <field name="name">res.company.form.inherit</field>
            <field name="model">res.company</field>
            <field name="inherit_id" ref="sale.view_company_inherit_form2"/>
            <field name="arch" type="xml">
                <group name="sale_grp"  position="after">
                    <newline/>
                    <group>
                        <field name="sale_order_dummy_confirm"/>
                    </group>
                </group>
            </field>
        </record>
    </data>
</openerp>
